LAGEF_UFF/LAGEF_UFF_Shoreline.py
LAGEF_UFF/__init__.py
lagef_uff_shoreline-0.1.0.dist-info/licenses/LICENCE
lagef_uff_shoreline-0.1.0.dist-info/METADATA
lagef_uff_shoreline-0.1.0.dist-info/WHEEL
lagef_uff_shoreline-0.1.0.dist-info/top_level.txt
lagef_uff_shoreline-0.1.0.dist-info/RECORD
