Metadata-Version: 2.4
Name: LAGEF-UFF-Shoreline
Version: 0.1.0
Summary: Scripts para análise de linha de costa - Lagef UFF - projeto IVC
Author: Pablo Simoes
Author-email: ['pablosergio.simoes@gmail.com', 'pablosimoes@id.uff.br']
License: MIT License
Keywords: lagef uff,linha de costa,shoreline,google earth engine
License-File: LICENCE
Requires-Dist: pandas
Requires-Dist: geemap
Requires-Dist: numpy
Requires-Dist: earthengine-api
Requires-Dist: scikit-image
Requires-Dist: matplotlib
Dynamic: author
Dynamic: author-email
Dynamic: description
Dynamic: description-content-type
Dynamic: keywords
Dynamic: license
Dynamic: license-file
Dynamic: requires-dist
Dynamic: summary
